django_migrate_sql-0.1.1.dist-info/DESCRIPTION.rst
django_migrate_sql-0.1.1.dist-info/METADATA
django_migrate_sql-0.1.1.dist-info/RECORD
django_migrate_sql-0.1.1.dist-info/WHEEL
django_migrate_sql-0.1.1.dist-info/metadata.json
django_migrate_sql-0.1.1.dist-info/top_level.txt
migrate_sql/__init__.py
migrate_sql/autodetector.py
migrate_sql/config.py
migrate_sql/graph.py
migrate_sql/operations.py
migrate_sql/management/__init__.py
migrate_sql/management/commands/__init__.py
migrate_sql/management/commands/makemigrations.py
tests/__init__.py
tests/manage.py
tests/test_app/__init__.py
tests/test_app/apps.py
tests/test_app/models.py
tests/test_app/sql_config.py
tests/test_app/test_migrations.py
tests/test_app/test_utils.py
tests/test_app/urls.py
tests/test_app/migrations/0001_initial.py
tests/test_app/migrations/__init__.py
tests/test_app/migrations_change/0001_initial.py
tests/test_app/migrations_change/0002_auto_20151224_1827.py
tests/test_app/migrations_change/__init__.py
tests/test_app/migrations_deps_delete/0001_initial.py
tests/test_app/migrations_deps_delete/0002_auto_20160106_0947.py
tests/test_app/migrations_deps_delete/0003_auto_20160108_0048.py
tests/test_app/migrations_deps_delete/0004_auto_20160108_0048.py
tests/test_app/migrations_deps_delete/__init__.py
tests/test_app/migrations_deps_update/0001_initial.py
tests/test_app/migrations_deps_update/0002_auto_20160106_0947.py
tests/test_app/migrations_deps_update/__init__.py
tests/test_app/migrations_recreate/0001_initial.py
tests/test_app/migrations_recreate/0002_auto_20151224_1827.py
tests/test_app/migrations_recreate/0003_auto_20160106_1038.py
tests/test_app/migrations_recreate/__init__.py
tests/test_app2/__init__.py
tests/test_app2/apps.py
tests/test_app2/models.py
tests/test_app2/sql_config.py
tests/test_app2/urls.py
tests/test_app2/migrations/__init__.py
tests/test_app2/migrations_deps_delete/0001_initial.py
tests/test_app2/migrations_deps_delete/0002_auto_20160108_0041.py
tests/test_app2/migrations_deps_delete/__init__.py
tests/test_app2/migrations_deps_update/0001_initial.py
tests/test_app2/migrations_deps_update/__init__.py
tests/test_project/__init__.py
tests/test_project/settings.py
tests/test_project/urls.py
