Metadata-Version: 2.0
Name: django-migrate-sql
Version: 0.1.1
Summary: Migration support for raw SQL in Django
Home-page: https://github.com/klichukb/django-migrate-sql
Author: Bogdan Klichuk
Author-email: klichukb@gmail.com
License: BSD
Platform: UNKNOWN
Classifier: Development Status :: 3 - Alpha
Classifier: Framework :: Django
Classifier: Intended Audience :: Developers
Classifier: License :: OSI Approved :: BSD License
Classifier: Natural Language :: English
Classifier: Programming Language :: Python :: 2.7
Classifier: Programming Language :: Python :: 3.3
Classifier: Programming Language :: Python :: 3.4
Classifier: Programming Language :: Python :: 3.5
